processing_image/__init__.py
processing_image/processing/__init__.py
processing_image/processing/combination.py
processing_image/processing/transformation.py
processing_image/utils/__init__.py
processing_image/utils/io.py
processing_image/utils/plot.py
processing_image-0.0.1.dist-info/LICENSE
processing_image-0.0.1.dist-info/METADATA
processing_image-0.0.1.dist-info/WHEEL
processing_image-0.0.1.dist-info/top_level.txt
processing_image-0.0.1.dist-info/RECORD
