Metadata-Version: 2.1
Name: processing-image
Version: 0.0.1
Summary: My short description
Home-page: https://github.com/BrenoVitoi/processing-image.git
Author: Souza Breno
Author-email: breno.vitoi@gmail.com
License: UNKNOWN
Platform: UNKNOWN
Requires-Python: >=3.5
Requires-Dist: matplotlib
Requires-Dist: numpy
Requires-Dist: scikit-image (>=0.14.1)
